eglogging/VERSION
eglogging/__init__.py
eglogging/eglogging.py
eglogging/eglogging_demo.py
eglogging/logger_config_DEFAULT.json
eglogging/logger_config_HUMAN.json
eglogging-1.1.0.dist-info/LICENSE
eglogging-1.1.0.dist-info/METADATA
eglogging-1.1.0.dist-info/WHEEL
eglogging-1.1.0.dist-info/top_level.txt
eglogging-1.1.0.dist-info/RECORD
