Metadata-Version: 2.1
Name: eglogging
Version: 1.1.0
Summary: Simple wrapper around the python logging module
Home-page: https://github.com/Ecogate/eglogging
Author: Ecogate
Author-email: eglogging@ecogate.com
License: MIT
Platform: UNKNOWN
Classifier: License :: OSI Approved :: MIT License
Classifier: Programming Language :: Python :: 3
Classifier: Programming Language :: Python :: 3.8
